{
    "store" : "my_efi_feature_store",
    "name" : "my_efi_model",
    "class" : "org.apache.solr.ltr.model.LinearModel",
    "features" : [
      { 
        "name" : "maximize_votes"
      },
      { 
        "name" : "maximize_rating"
      },
      { 
        "name" : "review_bm25"
      },
      { 
        "name" : "description_bm25"
      },
      { 
        "name" : "original_score"
      }
    ],
    "params" : {
      "weights" : {
        "review_bm25": 0.0,
        "description_bm25": 0.0,
        "maximize_votes": 0.0,
        "maximize_rating": 0.0,
        "original_score" : 1.0
      }
    }
}